pof/__init__.py
pof/__main__.py
pof/cli.py
pof/cli_v2.py
pof/errors.py
pof/logger.py
pof/main.py
pof/evasion/__init__.py
pof/evasion/argv.py
pof/evasion/base.py
pof/evasion/integrity.py
pof/evasion/multi.py
pof/evasion/utils.py
pof/evasion/cpu/__init__.py
pof/evasion/cpu/cpu_count.py
pof/evasion/fs/__init__.py
pof/evasion/fs/directory_exist.py
pof/evasion/fs/directory_list_exist.py
pof/evasion/fs/directory_list_missing.py
pof/evasion/fs/directory_missing.py
pof/evasion/fs/exec_method.py
pof/evasion/fs/executable_path.py
pof/evasion/fs/file_exist.py
pof/evasion/fs/file_list_exist.py
pof/evasion/fs/file_list_missing.py
pof/evasion/fs/file_missing.py
pof/evasion/fs/tmp.py
pof/evasion/hardware/__init__.py
pof/evasion/hardware/ram_count.py
pof/evasion/hooks/__init__.py
pof/evasion/hooks/debugger.py
pof/evasion/hooks/tracemalloc.py
pof/evasion/human/__init__.py
pof/evasion/human/p.py
pof/evasion/human/prompt.py
pof/evasion/os/__init__.py
pof/evasion/os/domain.py
pof/evasion/os/hostname.py
pof/evasion/os/uid.py
pof/evasion/os/username.py
pof/evasion/processes/__init__.py
pof/evasion/processes/proc_count.py
pof/evasion/time/__init__.py
pof/evasion/time/expire.py
pof/evasion/time/uptime.py
pof/evasion/time/utc.py
pof/obfuscator/__init__.py
pof/obfuscator/boolean.py
pof/obfuscator/builtins.py
pof/obfuscator/constants.py
pof/obfuscator/definitions.py
pof/obfuscator/extract_variables.py
pof/obfuscator/names.py
pof/obfuscator/names_rope.py
pof/obfuscator/numbers.py
pof/obfuscator/restructure.py
pof/obfuscator/strings.py
pof/obfuscator/cipher/__init__.py
pof/obfuscator/cipher/deep_encryption.py
pof/obfuscator/cipher/rc4.py
pof/obfuscator/cipher/shift.py
pof/obfuscator/cipher/xor.py
pof/obfuscator/compression/__init__.py
pof/obfuscator/compression/bz2.py
pof/obfuscator/compression/gzip.py
pof/obfuscator/compression/lzma.py
pof/obfuscator/compression/zlib.py
pof/obfuscator/encoding/__init__.py
pof/obfuscator/encoding/a85.py
pof/obfuscator/encoding/b16.py
python_obfuscation_framework-1.8.0.dist-info/licenses/LICENSE
python_obfuscation_framework-1.8.0.dist-info/METADATA
python_obfuscation_framework-1.8.0.dist-info/WHEEL
python_obfuscation_framework-1.8.0.dist-info/entry_points.txt
python_obfuscation_framework-1.8.0.dist-info/top_level.txt
python_obfuscation_framework-1.8.0.dist-info/RECORD
