Metadata-Version: 2.4
Name: python-obfuscation-framework
Version: 1.8.0
Summary: Python Obfuscation Framework
Author-email: deoktr <35725720+deoktr@users.noreply.github.com>
Maintainer-email: deoktr <35725720+deoktr@users.noreply.github.com>
License-Expression: GPL-3.0-or-later
Project-URL: Homepage, https://github.com/deoktr/pof
Project-URL: Bug Reports, https://github.com/deoktr/pof/issues
Project-URL: Source, https://github.com/deoktr/pof/
Keywords: cybersecurity,obfuscation,obfuscator,stager,payload
Classifier: Development Status :: 4 - Beta
Classifier: Intended Audience :: Developers
Classifier: Natural Language :: English
Classifier: Programming Language :: Python :: 3
Classifier: Programming Language :: Python :: 3.5
Classifier: Programming Language :: Python :: 3.6
Classifier: Programming Language :: Python :: 3.7
Classifier: Programming Language :: Python :: 3.8
Classifier: Programming Language :: Python :: 3.9
Classifier: Programming Language :: Python :: 3.10
Classifier: Programming Language :: Python :: 3.11
Classifier: Programming Language :: Python :: 3.12
Classifier: Programming Language :: Python :: 3.13
Classifier: Programming Language :: Python :: 3.14
Classifier: Topic :: Security
Requires-Python: >=3.5
License-File: LICENSE
Requires-Dist: rope>=1.0.0
Requires-Dist: Pillow>=10.0.0
Requires-Dist: black>=25.0.0
Provides-Extra: dev
Requires-Dist: ruff==0.14.4; extra == "dev"
Requires-Dist: black==25.9.0; extra == "dev"
Requires-Dist: pyinstrument; extra == "dev"
Provides-Extra: test
Requires-Dist: pytest; extra == "test"
Requires-Dist: pytest-cov; extra == "test"
Provides-Extra: build
Requires-Dist: build; extra == "build"
Requires-Dist: twine; extra == "build"
Requires-Dist: check-manifest; extra == "build"
Dynamic: license-file
